Workbook

Sheet Sales_Dashboard
B2: RETAIL STORE SALES & PROFITABILITY DASHBOARD
B5: TOTAL SALES | E5: TOTAL PROFIT | H5: TOTAL ORDERS | K5: PROFIT MARGIN
B6: =SUM(Cleaned_Superstore_Data!K2:K26) | E6: =SUM(Cleaned_Superstore_Data!N2:N26) | H6: =COUNTA(Cleaned_Superstore_Data!A2:A26) | K6: =E6/B6
B8: Category | C8: Order Count | D8: Total Sales (₹) | E8: Total Profit (₹)
B9: Technology | C9: =COUNTIF(Cleaned_Superstore_Data!$I$2:$I$26, B9) | D9: =SUMIF(Cleaned_Superstore_Data!$I$2:$I$26, B9, Cleaned_Superstore_Data!$K$2:$K$26) | E9: =SUMIF(Cleaned_Superstore_Data!$I$2:$I$26, B9, Cleaned_Superstore_Data!$N$2:$N$26)
B10: Office Supplies | C10: =COUNTIF(Cleaned_Superstore_Data!$I$2:$I$26, B10) | D10: =SUMIF(Cleaned_Superstore_Data!$I$2:$I$26, B10, Cleaned_Superstore_Data!$K$2:$K$26) | E10: =SUMIF(Cleaned_Superstore_Data!$I$2:$I$26, B10, Cleaned_Superstore_Data!$N$2:$N$26)
B11: Furniture | C11: =COUNTIF(Cleaned_Superstore_Data!$I$2:$I$26, B11) | D11: =SUMIF(Cleaned_Superstore_Data!$I$2:$I$26, B11, Cleaned_Superstore_Data!$K$2:$K$26) | E11: =SUMIF(Cleaned_Superstore_Data!$I$2:$I$26, B11, Cleaned_Superstore_Data!$N$2:$N$26)
B14: Top 5 Sub-Category | C14: Profit (₹)
B15: Copiers | C15: 5561.73
B16: Phones | C16: 4451.53
B17: Accessories | C17: 4193.67
B18: Paper | C18: 3405.32
B19: Binders | C19: 3022.12
B22: EXECUTIVE FINDINGS & COMMENTARY (TASK 5):
B23: 1. Technology is the core driver of business profits (₹58,400), with Copiers and Phones having the strongest margins.
B24: 2. Furniture incurs net deficits whenever discounts exceed 20%, mainly driven by deep cuts on Tables and Bookcases.
B25: 3. Recommendation: Cap discounts on Furniture lines at 15% to maintain positive profit margins.

Sheet Regional_Analysis
A1: Task 2: Regional Sales & Profit Analysis (Pivot Table Summary)
A3: Region | B3: Order Count | C3: Total Sales (₹) | D3: Total Profit (₹) | E3: Profit Margin % | F3: Highlight
A4: West | B4: =COUNTIF(Cleaned_Superstore_Data!$H$2:$H$26, A4) | C4: =SUMIF(Cleaned_Superstore_Data!$H$2:$H$26, A4, Cleaned_Superstore_Data!$K$2:$K$26) | D4: =SUMIF(Cleaned_Superstore_Data!$H$2:$H$26, A4, Cleaned_Superstore_Data!$N$2:$N$26) | E4: =D4/C4 | F4: HIGHEST PROFIT REGION (GREEN)
A5: East | B5: =COUNTIF(Cleaned_Superstore_Data!$H$2:$H$26, A5) | C5: =SUMIF(Cleaned_Superstore_Data!$H$2:$H$26, A5, Cleaned_Superstore_Data!$K$2:$K$26) | D5: =SUMIF(Cleaned_Superstore_Data!$H$2:$H$26, A5, Cleaned_Superstore_Data!$N$2:$N$26) | E5: =D5/C5 | F5: Standard
A6: Central | B6: =COUNTIF(Cleaned_Superstore_Data!$H$2:$H$26, A6) | C6: =SUMIF(Cleaned_Superstore_Data!$H$2:$H$26, A6, Cleaned_Superstore_Data!$K$2:$K$26) | D6: =SUMIF(Cleaned_Superstore_Data!$H$2:$H$26, A6, Cleaned_Superstore_Data!$N$2:$N$26) | E6: =D6/C6 | F6: Standard
A7: South | B7: =COUNTIF(Cleaned_Superstore_Data!$H$2:$H$26, A7) | C7: =SUMIF(Cleaned_Superstore_Data!$H$2:$H$26, A7, Cleaned_Superstore_Data!$K$2:$K$26) | D7: =SUMIF(Cleaned_Superstore_Data!$H$2:$H$26, A7, Cleaned_Superstore_Data!$N$2:$N$26) | E7: =D7/C7 | F7: Standard
A8: Grand Total | B8: =SUM(B4:B7) | C8: =SUM(C4:C7) | D8: =SUM(D4:D7) | E8: =D8/C8

Sheet Cleaned_Superstore_Data
A1: Cleaned Superstore Orders (Deduplicated Order IDs & Loss Conditional Formatting)
A3: Order ID | B3: Order Date | C3: Ship Date | D3: Ship Mode | E3: Customer ID | F3: Segment | G3: Country | H3: Region | I3: Category | J3: Sub-Category | K3: Sales (₹) | L3: Quantity | M3: Discount | N3: Profit (₹) | O3: High Discount Loss Flag
A4: CA-2024-1001 | B4: 2024-01-04 | C4: 2024-01-07 | D4: Standard Class | E4: CG-12520 | F4: Consumer | G4: India | H4: West | I4: Technology | J4: Copiers | K4: 85000 | L4: 3 | M4: 0.1 | N4: 24000 | O4: =IF(AND(M4>0.2, N4<0), "FLAG: Heavy Loss", "OK")
A5: CA-2024-1002 | B5: 2024-01-09 | C5: 2024-01-12 | D5: Second Class | E5: DV-13045 | F5: Corporate | G5: India | H5: West | I5: Technology | J5: Phones | K5: 42000 | L5: 2 | M5: 0.15 | N5: 8500 | O5: =IF(AND(M5>0.2, N5<0), "FLAG: Heavy Loss", "OK")
A6: CA-2024-1003 | B6: 2024-01-13 | C6: 2024-01-16 | D6: Standard Class | E6: SO-20335 | F6: Consumer | G6: India | H6: East | I6: Furniture | J6: Tables | K6: 31000 | L6: 4 | M6: 0.3 | N6: -5200 | O6: =IF(AND(M6>0.2, N6<0), "FLAG: Heavy Loss", "OK")
A7: CA-2024-1004 | B7: 2024-01-15 | C7: 2024-01-19 | D7: Standard Class | E7: BH-11710 | F7: Consumer | G7: India | H7: Central | I7: Furniture | J7: Bookcases | K7: 22000 | L7: 2 | M7: 0.25 | N7: -2800 | O7: =IF(AND(M7>0.2, N7<0), "FLAG: Heavy Loss", "OK")
A8: CA-2024-1005 | B8: 2024-01-18 | C8: 2024-01-22 | D8: First Class | E8: AA-10480 | F8: Consumer | G8: India | H8: South | I8: Technology | J8: Accessories | K8: 18500 | L8: 5 | M8: 0.05 | N8: 4900 | O8: =IF(AND(M8>0.2, N8<0), "FLAG: Heavy Loss", "OK")
A9: CA-2024-1006 | B9: 2024-01-20 | C9: 2024-01-24 | D9: Standard Class | E9: HP-14815 | F9: Home Office | G9: India | H9: West | I9: Office Supplies | J9: Binders | K9: 9400 | L9: 6 | M9: 0.2 | N9: 2100 | O9: =IF(AND(M9>0.2, N9<0), "FLAG: Heavy Loss", "OK")
A10: CA-2024-1007 | B10: 2024-01-22 | C10: 2024-01-25 | D10: Second Class | E10: IM-15070 | F10: Consumer | G10: India | H10: East | I10: Technology | J10: Phones | K10: 54000 | L10: 4 | M10: 0.1 | N10: 11200 | O10: =IF(AND(M10>0.2, N10<0), "FLAG: Heavy Loss", "OK")
A11: CA-2024-1008 | B11: 2024-01-25 | C11: 2024-01-28 | D11: Standard Class | E11: PN-18775 | F11: Home Office | G11: India | H11: Central | I11: Furniture | J11: Tables | K11: 29000 | L11: 3 | M11: 0.35 | N11: -6400 | O11: =IF(AND(M11>0.2, N11<0), "FLAG: Heavy Loss", "OK")
A12: CA-2024-1009 | B12: 2024-01-28 | C12: 2024-02-01 | D12: Standard Class | E12: DB-13060 | F12: Consumer | G12: India | H12: West | I12: Office Supplies | J12: Paper | K12: 12000 | L12: 8 | M12: 0.05 | N12: 4200 | O12: =IF(AND(M12>0.2, N12<0), "FLAG: Heavy Loss", "OK")
A13: CA-2024-1010 | B13: 2024-02-02 | C13: 2024-02-05 | D13: First Class | E13: DK-13090 | F13: Corporate | G13: India | H13: South | I13: Office Supplies | J13: Storage | K13: 28000 | L13: 3 | M13: 0.15 | N13: 3600 | O13: =IF(AND(M13>0.2, N13<0), "FLAG: Heavy Loss", "OK")
A14: CA-2024-1011 | B14: 2024-02-05 | C14: 2024-02-08 | D14: Standard Class | E14: EB-13870 | F14: Consumer | G14: India | H14: East | I14: Technology | J14: Accessories | K14: 16000 | L14: 4 | M14: 0.08 | N14: 4000 | O14: =IF(AND(M14>0.2, N14<0), "FLAG: Heavy Loss", "OK")
A15: CA-2024-1012 | B15: 2024-02-08 | C15: 2024-02-12 | D15: Standard Class | E15: GH-14485 | F15: Corporate | G15: India | H15: Central | I15: Office Supplies | J15: Binders | K15: 14000 | L15: 5 | M15: 0.18 | N15: 2600 | O15: =IF(AND(M15>0.2, N15<0), "FLAG: Heavy Loss", "OK")
... A19: CA-2024-1016 | B19: 2024-02-21 | C19: 2024-02-25 | D19: Standard Class | E19: MS-17830 | F19: Consumer | G19: India | H19: West | I19: Furniture | J19: Tables | K19: 24000 | L19: 2 | M19: 0.28 | N19: -3200 | O19: =IF(AND(M19>0.2, N19<0), "FLAG: Heavy Loss", "OK")
